NoiseLabelDataset/NoiseLabelDataset.py
NoiseLabelDataset/__init__.py
NoiseLabelDataset/utils.py
noise_label_pkg-0.1.0.dist-info/METADATA
noise_label_pkg-0.1.0.dist-info/WHEEL
noise_label_pkg-0.1.0.dist-info/top_level.txt
noise_label_pkg-0.1.0.dist-info/RECORD
